{
  "schema_version": "1.0",
  "listing_id": "misceo",
  "category_path": "Equipment/Vacuum_Emulsifiers",
  "url": "https://misceo-cosmetics.com/",
  "company_name": "Misceo",
  "status": "active",
  "date_added": "2025-11-29",
  "date_updated": "2025-11-29",
  "website": "https://misceo-cosmetics.com/",
  "specializations": [
    "Emulsifier homogenizers",
    "1 to 100 litre capacity",
    "Portable emulsifiers",
    "Fixed emulsification systems",
    "Flexible capacity options"
  ],
  "product_highlights": [
    "Wide capacity range (1-100 litres)",
    "Portable options available",
    "Fixed installation systems",
    "Emulsifier homogenizers",
    "Flexible production solutions"
  ],
  "tags": [
    "vacuum-emulsifiers",
    "emulsifier-homogenizers",
    "portable-equipment",
    "1-100-litre",
    "cosmetics-equipment",
    "flexible-capacity",
    "manufacturing-equipment"
  ],
  "metadata": {
    "last_validated": "2025-11-29",
    "validation_method": "manual",
    "data_source": "research_critical_gaps_2025-11-28.md"
  },
  "notes": "Manufacturer of emulsifier homogenizers with capacity range from 1 to 100 litres. Offers both portable and fixed options for flexible cosmetics production."
}
