{
  "schema_version": "1.0",
  "listing_id": "silverson",
  "category_path": "Equipment/Vacuum_Emulsifiers",
  "url": "https://www.silverson.com",
  "company_name": "Silverson",
  "status": "active",
  "date_added": "2025-11-29",
  "date_updated": "2025-11-29",
  "address": "United Kingdom, Global operations",
  "country": "United Kingdom",
  "phone": "",
  "email": "",
  "website": "https://www.silverson.com",
  "specializations": [
    "Industrial mixers and emulsifiers",
    "Vacuum emulsification",
    "High-shear mixing",
    "Laboratory to production scale",
    "Quality engineering",
    "Technical support",
    "Process optimization"
  ],
  "certifications": [],
  "tags": [
    "vacuum-emulsifiers",
    "industrial-mixers",
    "high-shear-mixing",
    "scalable-equipment",
    "quality-engineering",
    "technical-support",
    "uk-manufacturer"
  ],
  "metadata": {
    "last_validated": "2025-11-29",
    "validation_method": "manual",
    "data_source": "research_specialized_equipment_2025-11-29.md"
  },
  "notes": "Established European manufacturer of industrial mixers and emulsifiers with reputation for quality and precision. Offers vacuum emulsification and high-shear mixing equipment from laboratory to production scale. Provides comprehensive technical support and process optimization services."
}
