{
  "schema_version": "1.0",
  "listing_id": "yz_zhitong",
  "category_path": "Equipment/Vacuum_Emulsifiers",
  "url": "https://yzzhitong.com/",
  "company_name": "YZ Zhitong",
  "status": "active",
  "date_added": "2025-11-29",
  "date_updated": "2025-11-29",
  "website": "https://yzzhitong.com/",
  "specializations": [
    "Lab vacuum emulsifier and homogenizer",
    "Complete mixing, dispersing, emulsifying process",
    "High-speed motor systems",
    "Long-life design",
    "Laboratory-scale equipment"
  ],
  "product_highlights": [
    "Lab-scale vacuum emulsifiers",
    "Complete emulsification process",
    "High-speed motor technology",
    "Durable long-life design",
    "Mixing, dispersing, and emulsifying capabilities"
  ],
  "tags": [
    "vacuum-emulsifiers",
    "laboratory-equipment",
    "homogenizers",
    "high-speed-motor",
    "mixing-equipment",
    "dispersing-equipment",
    "lab-scale"
  ],
  "metadata": {
    "last_validated": "2025-11-29",
    "validation_method": "manual",
    "data_source": "research_critical_gaps_2025-11-28.md"
  },
  "notes": "Manufacturer of lab-scale vacuum emulsifiers and homogenizers with complete mixing, dispersing, and emulsifying capabilities. Features high-speed motor and long-life design."
}
