{
  "schema_version": "1.0",
  "listing_id": "sd_foods_centella_asiatica",
  "category_path": "Raw_Materials/Centella_Asiatica",
  "url": "https://www.usetorg.com",
  "company_name": "SD Foods",
  "status": "active",
  "date_added": "2025-12-10",
  "date_updated": "2025-12-10",
  "country": "Europe",
  "website": "www.sdfoods.eu",
  "specializations": [
    "Private label Centella Asiatica Extract",
    "European cosmetics manufacturers",
    "Private label services",
    "European market focus"
  ],
  "tags": [
    "mid-range",
    "manufacturer",
    "europe",
    "private-label",
    "european-market"
  ],
  "metadata": {
    "last_validated": "2025-12-10",
    "validation_method": "manual",
    "data_source": "high_value_actives_research_dec_9_2025.md"
  },
  "notes": "European private label manufacturer. Centella Asiatica Extract for European cosmetics manufacturers. Listed on Usetorg.com Best Suppliers."
}
