{
  "schema_version": "1.0",
  "category_id": 9400,
  "listing_id": "sabinsa_corporation_retinoids",
  "category_path": "Raw_Materials/Retinoids",
  "url": "https://personalcaresuppliers.com/Listing/Index/Raw_Materials/Retinoids/9400/",
  "company_name": "Sabinsa Corporation",
  "status": "active",
  "date_added": "2025-11-16",
  "date_updated": "2025-11-16",
  "address": "750 S. Innovation Circle, Payson, UT 84651",
  "country": "United States",
  "phone": "732-777-1111",
  "specializations": [
    "Bakuchiol (natural retinol alternative)",
    "Cosmeceutical ingredients",
    "Standardized extracts",
    "Plant-based actives",
    "Anti-aging formulations"
  ],
  "product_highlights": [
    "Bakuchiol - natural retinol alternative",
    "No irritation or photosensitivity",
    "Plant-derived active",
    "Suitable for sensitive skin",
    "Clinical research support"
  ],
  "tags": [
    "retinoids",
    "bakuchiol",
    "retinol-alternative",
    "natural",
    "plant-based",
    "cosmeceuticals",
    "anti-aging",
    "major-player"
  ],
  "metadata": {
    "last_validated": "2025-11-16",
    "validation_method": "manual",
    "data_source": "research_retinoids_2025-11-16.md"
  },
  "notes": "Sabinsa Corporation is a major player in cosmeceutical ingredients, offering Bakuchiol as a natural retinol alternative with no irritation or photosensitivity concerns."
}
