{
  "schema_version": "1.0",
  "category_id": 9100,
  "listing_id": "lonza_niacinamide",
  "category_path": "Raw_Materials/Niacinamide",
  "url": "https://personalcaresuppliers.com/Listing/Index/Raw_Materials/Niacinamide/9100/",
  "company_name": "Lonza",
  "status": "active",
  "date_added": "2025-11-15",
  "date_updated": "2025-11-15",
  "country": "Switzerland",
  "specializations": [
    "Pharmaceutical-grade niacinamide",
    "Cosmetic-grade niacinamide",
    "High purity (99%+)",
    "USP/EP standards compliance",
    "Specialty ingredients manufacturing",
    "Quality certifications"
  ],
  "product_highlights": [
    "Pharmaceutical-grade niacinamide (USP, EP standards)",
    "Cosmetic-grade niacinamide",
    "High purity 99%+",
    "Global supply chain"
  ],
  "tags": [
    "major-player",
    "premium",
    "high-performance"
  ],
  "certifications": [
    "USP certified",
    "EP certified",
    "ISO certified",
    "GMP certified"
  ],
  "metadata": {
    "last_validated": "2025-11-15",
    "validation_method": "manual",
    "data_source": "research_niacinamide_2025-11-13.md"
  },
  "notes": "Major pharmaceutical and specialty ingredients manufacturer with pharmaceutical-grade (99%+) and cosmetic-grade niacinamide. Regulatory compliance and global supply chain."
}
